rio_stac_io/__init__.py
rio_stac_io/io.py
rio_stac_io/utils.py
rio_stac_io/drivers/__init__.py
rio_stac_io/drivers/gti.py
rio_stac_io/drivers/stacit.py
rio_stac_io/drivers/stacta.py
rio_stac_io-0.3.5.dist-info/METADATA
rio_stac_io-0.3.5.dist-info/WHEEL
rio_stac_io-0.3.5.dist-info/licenses/LICENSE
rio_stac_io-0.3.5.dist-info/RECORD
