Metadata-Version: 2.4
Name: rio-stac-io
Version: 0.3.5
Summary: A rasterio extension to open STAC Items and ItemCollections using native GDAL drivers
Author-email: Thomas Maschler <thomas.maschler@planet.com>
License-File: LICENSE
Requires-Python: >=3.10
Requires-Dist: pystac-client>=0.9.0
Requires-Dist: pystac>=1.11.0
Requires-Dist: rasterio>=1.4.3
Provides-Extra: gti
Requires-Dist: stac-geoparquet>=0.7.0; extra == 'gti'
